RelationCalculator/CalculatorClass.py
RelationCalculator/RelationsClass.py
RelationCalculator/__init__.py
RelationCalculator-0.0.6.dist-info/METADATA
RelationCalculator-0.0.6.dist-info/WHEEL
RelationCalculator-0.0.6.dist-info/top_level.txt
RelationCalculator-0.0.6.dist-info/RECORD
