Metadata-Version: 2.1
Name: RelationCalculator
Version: 0.0.6
Home-page: 
Author: sun
Author-email: 2022200814@mail.buct.edu.cn
Classifier: Programming Language :: Python :: 3
Classifier: License :: OSI Approved :: MIT License
Classifier: Operating System :: OS Independent
Requires-Dist: numpy
Requires-Dist: matplotlib
